{"units": "", "country": "\u00a0Shaded cells indicate IMF staff estimates", "percent": 0, "desc": ""}
{"units": "", "country": "", "percent": 0, "desc": ""}
{"units": "Percent change", "country": "Afghanistan", "percent": 0, "desc": "Volume of imports of goods and services"}
{"units": "Percent change", "country": "Albania", "percent": 0.0, "desc": "Volume of imports of goods and services"}
{"units": "Percent change", "country": "Algeria", "percent": -28.7, "desc": "Volume of imports of goods and services"}
{"units": "Percent change", "country": "Angola", "percent": -1.5, "desc": "Volume of imports of goods and services"}
{"units": "Percent change", "country": "Antigua and Barbuda", "percent": 4.906, "desc": "Volume of imports of goods and services"}
{"units": "Percent change", "country": "Argentina", "percent": 11.422, "desc": "Volume of imports of goods and services"}
{"units": "Percent change", "country": "Armenia", "percent": 0, "desc": "Volume of imports of goods and services"}
{"units": "Percent change", "country": "Australia", "percent": 2.516, "desc": "Volume of imports of goods and services"}
{"units": "Percent change", "country": "Austria", "percent": 5.447, "desc": "Volume of imports of goods and services"}
{"units": "Percent change", "country": "Azerbaijan", "percent": 0, "desc": "Volume of imports of goods and services"}
{"units": "Percent change", "country": "The Bahamas", "percent": -3.267, "desc": "Volume of imports of goods and services"}
{"units": "Percent change", "country": "Bahrain", "percent": 0, "desc": "Volume of imports of goods and services"}
{"units": "Percent change", "country": "Bangladesh", "percent": 7.84, "desc": "Volume of imports of goods and services"}
{"units": "Percent change", "country": "Barbados", "percent": -15.004, "desc": "Volume of imports of goods and services"}
{"units": "Percent change", "country": "Belarus", "percent": 0, "desc": "Volume of imports of goods and services"}
{"units": "Percent change", "country": "Belgium", "percent": 6.837, "desc": "Volume of imports of goods and services"}
{"units": "Percent change", "country": "Belize", "percent": 0, "desc": "Volume of imports of goods and services"}
{"units": "Percent change", "country": "Benin", "percent": 9.944, "desc": "Volume of imports of goods and services"}
{"units": "Percent change", "country": "Bhutan", "percent": -4.87, "desc": "Volume of imports of goods and services"}
{"units": "Percent change", "country": "Bolivia", "percent": 7.734, "desc": "Volume of imports of goods and services"}
{"units": "Percent change", "country": "Bosnia and Herzegovina", "percent": 0, "desc": "Volume of imports of goods and services"}
{"units": "Percent change", "country": "Botswana", "percent": 13.874, "desc": "Volume of imports of goods and services"}
{"units": "Percent change", "country": "Brazil", "percent": -3.209, "desc": "Volume of imports of goods and services"}
{"units": "Percent change", "country": "Brunei Darussalam", "percent": -15.029, "desc": "Volume of imports of goods and services"}
{"units": "Percent change", "country": "Bulgaria", "percent": 21.713, "desc": "Volume of imports of goods and services"}
{"units": "Percent change", "country": "Burkina Faso", "percent": 6.079, "desc": "Volume of imports of goods and services"}
{"units": "Percent change", "country": "Burundi", "percent": -14.224, "desc": "Volume of imports of goods and services"}
{"units": "Percent change", "country": "Cabo Verde", "percent": -7.5, "desc": "Volume of imports of goods and services"}
{"units": "Percent change", "country": "Cambodia", "percent": -1.803, "desc": "Volume of imports of goods and services"}
{"units": "Percent change", "country": "Cameroon", "percent": -9.705, "desc": "Volume of imports of goods and services"}
{"units": "Percent change", "country": "Canada", "percent": 5.431, "desc": "Volume of imports of goods and services"}
{"units": "Percent change", "country": "Central African Republic", "percent": 282.627, "desc": "Volume of imports of goods and services"}
{"units": "Percent change", "country": "Chad", "percent": -6.968, "desc": "Volume of imports of goods and services"}
{"units": "Percent change", "country": "Chile", "percent": 18.61, "desc": "Volume of imports of goods and services"}
{"units": "Percent change", "country": "China", "percent": 0, "desc": "Volume of imports of goods and services"}
{"units": "Percent change", "country": "Colombia", "percent": 4.906, "desc": "Volume of imports of goods and services"}
{"units": "Percent change", "country": "Comoros", "percent": -23.033, "desc": "Volume of imports of goods and services"}
{"units": "Percent change", "country": "Democratic Republic of the Congo", "percent": 0, "desc": "Volume of imports of goods and services"}
{"units": "Percent change", "country": "Republic of Congo", "percent": 19.956, "desc": "Volume of imports of goods and services"}
{"units": "Percent change", "country": "Costa Rica", "percent": 17.582, "desc": "Volume of imports of goods and services"}
{"units": "Percent change", "country": "C\u00f4te d'Ivoire", "percent": 4.0, "desc": "Volume of imports of goods and services"}
{"units": "Percent change", "country": "Croatia", "percent": 0, "desc": "Volume of imports of goods and services"}
{"units": "Percent change", "country": "Cyprus", "percent": 8.809, "desc": "Volume of imports of goods and services"}
{"units": "Percent change", "country": "Czech Republic", "percent": 0, "desc": "Volume of imports of goods and services"}
{"units": "Percent change", "country": "Denmark", "percent": -1.178, "desc": "Volume of imports of goods and services"}
{"units": "Percent change", "country": "Djibouti", "percent": 0, "desc": "Volume of imports of goods and services"}
{"units": "Percent change", "country": "Dominica", "percent": 8.511, "desc": "Volume of imports of goods and services"}
{"units": "Percent change", "country": "Dominican Republic", "percent": 6.836, "desc": "Volume of imports of goods and services"}
{"units": "Percent change", "country": "Ecuador", "percent": 9.719, "desc": "Volume of imports of goods and services"}
{"units": "Percent change", "country": "Egypt", "percent": -4.583, "desc": "Volume of imports of goods and services"}
{"units": "Percent change", "country": "El Salvador", "percent": 0.0, "desc": "Volume of imports of goods and services"}
{"units": "Percent change", "country": "Equatorial Guinea", "percent": 83.915, "desc": "Volume of imports of goods and services"}
{"units": "Percent change", "country": "Eritrea", "percent": 0, "desc": "Volume of imports of goods and services"}
{"units": "Percent change", "country": "Estonia", "percent": 0, "desc": "Volume of imports of goods and services"}
{"units": "Percent change", "country": "Ethiopia", "percent": 17.98, "desc": "Volume of imports of goods and services"}
{"units": "Percent change", "country": "Fiji", "percent": 0, "desc": "Volume of imports of goods and services"}
{"units": "Percent change", "country": "Finland", "percent": 8.79, "desc": "Volume of imports of goods and services"}
{"units": "Percent change", "country": "France", "percent": 7.704, "desc": "Volume of imports of goods and services"}
{"units": "Percent change", "country": "Gabon", "percent": -41.893, "desc": "Volume of imports of goods and services"}
{"units": "Percent change", "country": "The Gambia", "percent": 0, "desc": "Volume of imports of goods and services"}
{"units": "Percent change", "country": "Georgia", "percent": 0, "desc": "Volume of imports of goods and services"}
{"units": "Percent change", "country": "Germany", "percent": 4.584, "desc": "Volume of imports of goods and services"}
{"units": "Percent change", "country": "Ghana", "percent": 17.41, "desc": "Volume of imports of goods and services"}
{"units": "Percent change", "country": "Greece", "percent": 2.141, "desc": "Volume of imports of goods and services"}
{"units": "Percent change", "country": "Grenada", "percent": -0.029, "desc": "Volume of imports of goods and services"}
{"units": "Percent change", "country": "Guatemala", "percent": 23.846, "desc": "Volume of imports of goods and services"}
{"units": "Percent change", "country": "Guinea", "percent": 0, "desc": "Volume of imports of goods and services"}
{"units": "Percent change", "country": "Guinea-Bissau", "percent": -18.3, "desc": "Volume of imports of goods and services"}
{"units": "Percent change", "country": "Guyana", "percent": -9.41, "desc": "Volume of imports of goods and services"}
{"units": "Percent change", "country": "Haiti", "percent": 1.753, "desc": "Volume of imports of goods and services"}
{"units": "Percent change", "country": "Honduras", "percent": -3.033, "desc": "Volume of imports of goods and services"}
{"units": "Percent change", "country": "Hong Kong SAR", "percent": 28.534, "desc": "Volume of imports of goods and services"}
{"units": "Percent change", "country": "Hungary", "percent": 2.914, "desc": "Volume of imports of goods and services"}
{"units": "Percent change", "country": "Iceland", "percent": 23.265, "desc": "Volume of imports of goods and services"}
{"units": "Percent change", "country": "India", "percent": 2.058, "desc": "Volume of imports of goods and services"}
{"units": "Percent change", "country": "Indonesia", "percent": 24.4, "desc": "Volume of imports of goods and services"}
{"units": "Percent change", "country": "Islamic Republic of Iran", "percent": 6.255, "desc": "Volume of imports of goods and services"}
{"units": "Percent change", "country": "Iraq", "percent": 0, "desc": "Volume of imports of goods and services"}
{"units": "Percent change", "country": "Ireland", "percent": 7.298, "desc": "Volume of imports of goods and services"}
{"units": "Percent change", "country": "Israel", "percent": 18.962, "desc": "Volume of imports of goods and services"}
{"units": "Percent change", "country": "Italy", "percent": 12.033, "desc": "Volume of imports of goods and services"}
{"units": "Percent change", "country": "Jamaica", "percent": 5.486, "desc": "Volume of imports of goods and services"}
{"units": "Percent change", "country": "Japan", "percent": 9.018, "desc": "Volume of imports of goods and services"}
{"units": "Percent change", "country": "Jordan", "percent": 7.523, "desc": "Volume of imports of goods and services"}
{"units": "Percent change", "country": "Kazakhstan", "percent": 0, "desc": "Volume of imports of goods and services"}
{"units": "Percent change", "country": "Kenya", "percent": 13.3, "desc": "Volume of imports of goods and services"}
{"units": "Percent change", "country": "Kiribati", "percent": 138.908, "desc": "Volume of imports of goods and services"}
{"units": "Percent change", "country": "Korea", "percent": 19.559, "desc": "Volume of imports of goods and services"}
{"units": "Percent change", "country": "Kosovo", "percent": 0, "desc": "Volume of imports of goods and services"}
{"units": "Percent change", "country": "Kuwait", "percent": -9.179, "desc": "Volume of imports of goods and services"}
{"units": "Percent change", "country": "Kyrgyz Republic", "percent": 0, "desc": "Volume of imports of goods and services"}
{"units": "Percent change", "country": "Lao P.D.R.", "percent": 6.048, "desc": "Volume of imports of goods and services"}
{"units": "Percent change", "country": "Latvia", "percent": 0, "desc": "Volume of imports of goods and services"}
{"units": "Percent change", "country": "Lebanon", "percent": -8.813, "desc": "Volume of imports of goods and services"}
{"units": "Percent change", "country": "Lesotho", "percent": 0, "desc": "Volume of imports of goods and services"}
{"units": "Percent change", "country": "Liberia", "percent": 0, "desc": "Volume of imports of goods and services"}
{"units": "Percent change", "country": "Libya", "percent": 0, "desc": "Volume of imports of goods and services"}
{"units": "Percent change", "country": "Lithuania", "percent": 0, "desc": "Volume of imports of goods and services"}
{"units": "Percent change", "country": "Luxembourg", "percent": 7.306, "desc": "Volume of imports of goods and services"}
{"units": "Percent change", "country": "Macao SAR", "percent": 0, "desc": "Volume of imports of goods and services"}
{"units": "Percent change", "country": "FYR Macedonia", "percent": 0, "desc": "Volume of imports of goods and services"}
{"units": "Percent change", "country": "Madagascar", "percent": 3.777, "desc": "Volume of imports of goods and services"}
{"units": "Percent change", "country": "Malawi", "percent": -2.863, "desc": "Volume of imports of goods and services"}
{"units": "Percent change", "country": "Malaysia", "percent": 8.474, "desc": "Volume of imports of goods and services"}
{"units": "Percent change", "country": "Maldives", "percent": 3.651, "desc": "Volume of imports of goods and services"}
{"units": "Percent change", "country": "Mali", "percent": -4.076, "desc": "Volume of imports of goods and services"}
{"units": "Percent change", "country": "Malta", "percent": 14.029, "desc": "Volume of imports of goods and services"}
{"units": "Percent change", "country": "Marshall Islands", "percent": 0, "desc": "Volume of imports of goods and services"}
{"units": "Percent change", "country": "Mauritania", "percent": 0, "desc": "Volume of imports of goods and services"}
{"units": "Percent change", "country": "Mauritius", "percent": 15.791, "desc": "Volume of imports of goods and services"}
{"units": "Percent change", "country": "Mexico", "percent": 3.625, "desc": "Volume of imports of goods and services"}
{"units": "Percent change", "country": "Micronesia", "percent": 0, "desc": "Volume of imports of goods and services"}
{"units": "Percent change", "country": "Moldova", "percent": 0, "desc": "Volume of imports of goods and services"}
{"units": "Percent change", "country": "Mongolia", "percent": 0, "desc": "Volume of imports of goods and services"}
{"units": "Percent change", "country": "Montenegro", "percent": 0, "desc": "Volume of imports of goods and services"}
{"units": "Percent change", "country": "Morocco", "percent": -3.891, "desc": "Volume of imports of goods and services"}
{"units": "Percent change", "country": "Mozambique", "percent": 6.21, "desc": "Volume of imports of goods and services"}
{"units": "Percent change", "country": "Myanmar", "percent": 0, "desc": "Volume of imports of goods and services"}
{"units": "Percent change", "country": "Namibia", "percent": 0, "desc": "Volume of imports of goods and services"}
{"units": "Percent change", "country": "Nepal", "percent": 0, "desc": "Volume of imports of goods and services"}
{"units": "Percent change", "country": "Netherlands", "percent": 1.935, "desc": "Volume of imports of goods and services"}
{"units": "Percent change", "country": "New Zealand", "percent": -13.915, "desc": "Volume of imports of goods and services"}
{"units": "Percent change", "country": "Nicaragua", "percent": 0, "desc": "Volume of imports of goods and services"}
{"units": "Percent change", "country": "Niger", "percent": 22.753, "desc": "Volume of imports of goods and services"}
{"units": "Percent change", "country": "Nigeria", "percent": 0, "desc": "Volume of imports of goods and services"}
{"units": "Percent change", "country": "Norway", "percent": -6.375, "desc": "Volume of imports of goods and services"}
{"units": "Percent change", "country": "Oman", "percent": -31.593, "desc": "Volume of imports of goods and services"}
{"units": "Percent change", "country": "Pakistan", "percent": 1.916, "desc": "Volume of imports of goods and services"}
{"units": "Percent change", "country": "Palau", "percent": 0, "desc": "Volume of imports of goods and services"}
{"units": "Percent change", "country": "Panama", "percent": 4.729, "desc": "Volume of imports of goods and services"}
{"units": "Percent change", "country": "Papua New Guinea", "percent": 0, "desc": "Volume of imports of goods and services"}
{"units": "Percent change", "country": "Paraguay", "percent": 15.0, "desc": "Volume of imports of goods and services"}
{"units": "Percent change", "country": "Peru", "percent": 13.786, "desc": "Volume of imports of goods and services"}
{"units": "Percent change", "country": "Philippines", "percent": 22.177, "desc": "Volume of imports of goods and services"}
{"units": "Percent change", "country": "Poland", "percent": 0, "desc": "Volume of imports of goods and services"}
{"units": "Percent change", "country": "Portugal", "percent": 27.402, "desc": "Volume of imports of goods and services"}
{"units": "Percent change", "country": "Puerto Rico", "percent": 0, "desc": "Volume of imports of goods and services"}
{"units": "Percent change", "country": "Qatar", "percent": 4.253, "desc": "Volume of imports of goods and services"}
{"units": "Percent change", "country": "Romania", "percent": -1.042, "desc": "Volume of imports of goods and services"}
{"units": "Percent change", "country": "Russia", "percent": 0, "desc": "Volume of imports of goods and services"}
{"units": "Percent change", "country": "Rwanda", "percent": -6.834, "desc": "Volume of imports of goods and services"}
{"units": "Percent change", "country": "Samoa", "percent": 0, "desc": "Volume of imports of goods and services"}
{"units": "Percent change", "country": "San Marino", "percent": 0, "desc": "Volume of imports of goods and services"}
{"units": "Percent change", "country": "S\u00e3o Tom\u00e9 and Pr\u00edncipe", "percent": 0.0, "desc": "Volume of imports of goods and services"}
{"units": "Percent change", "country": "Saudi Arabia", "percent": -10.042, "desc": "Volume of imports of goods and services"}
{"units": "Percent change", "country": "Senegal", "percent": -7.533, "desc": "Volume of imports of goods and services"}
{"units": "Percent change", "country": "Serbia", "percent": 0, "desc": "Volume of imports of goods and services"}
{"units": "Percent change", "country": "Seychelles", "percent": 98.796, "desc": "Volume of imports of goods and services"}
{"units": "Percent change", "country": "Sierra Leone", "percent": 16.461, "desc": "Volume of imports of goods and services"}
{"units": "Percent change", "country": "Singapore", "percent": 13.327, "desc": "Volume of imports of goods and services"}
{"units": "Percent change", "country": "Slovak Republic", "percent": 0, "desc": "Volume of imports of goods and services"}
{"units": "Percent change", "country": "Slovenia", "percent": 0, "desc": "Volume of imports of goods and services"}
{"units": "Percent change", "country": "Solomon Islands", "percent": -15.046, "desc": "Volume of imports of goods and services"}
{"units": "Percent change", "country": "South Africa", "percent": 3.494, "desc": "Volume of imports of goods and services"}
{"units": "Percent change", "country": "South Sudan", "percent": 0, "desc": "Volume of imports of goods and services"}
{"units": "Percent change", "country": "Spain", "percent": 24.787, "desc": "Volume of imports of goods and services"}
{"units": "Percent change", "country": "Sri Lanka", "percent": 0.0, "desc": "Volume of imports of goods and services"}
{"units": "Percent change", "country": "St. Kitts and Nevis", "percent": 26.57, "desc": "Volume of imports of goods and services"}
{"units": "Percent change", "country": "St. Lucia", "percent": 5.309, "desc": "Volume of imports of goods and services"}
{"units": "Percent change", "country": "St. Vincent and the Grenadines", "percent": 5.288, "desc": "Volume of imports of goods and services"}
{"units": "Percent change", "country": "Sudan", "percent": 0.457, "desc": "Volume of imports of goods and services"}
{"units": "Percent change", "country": "Suriname", "percent": -4.276, "desc": "Volume of imports of goods and services"}
{"units": "Percent change", "country": "Swaziland", "percent": 16.739, "desc": "Volume of imports of goods and services"}
{"units": "Percent change", "country": "Sweden", "percent": 19.906, "desc": "Volume of imports of goods and services"}
{"units": "Percent change", "country": "Switzerland", "percent": -1.58, "desc": "Volume of imports of goods and services"}
{"units": "Percent change", "country": "Syria", "percent": 18.2, "desc": "Volume of imports of goods and services"}
{"units": "Percent change", "country": "Taiwan Province of China", "percent": 28.115, "desc": "Volume of imports of goods and services"}
{"units": "Percent change", "country": "Tajikistan", "percent": 0, "desc": "Volume of imports of goods and services"}
{"units": "Percent change", "country": "Tanzania", "percent": 123.1, "desc": "Volume of imports of goods and services"}
{"units": "Percent change", "country": "Thailand", "percent": 27.063, "desc": "Volume of imports of goods and services"}
{"units": "Percent change", "country": "Timor-Leste", "percent": 0, "desc": "Volume of imports of goods and services"}
{"units": "Percent change", "country": "Togo", "percent": -8.731, "desc": "Volume of imports of goods and services"}
{"units": "Percent change", "country": "Tonga", "percent": 0, "desc": "Volume of imports of goods and services"}
{"units": "Percent change", "country": "Trinidad and Tobago", "percent": -26.274, "desc": "Volume of imports of goods and services"}
{"units": "Percent change", "country": "Tunisia", "percent": -3.447, "desc": "Volume of imports of goods and services"}
{"units": "Percent change", "country": "Turkey", "percent": 0, "desc": "Volume of imports of goods and services"}
{"units": "Percent change", "country": "Turkmenistan", "percent": 0, "desc": "Volume of imports of goods and services"}
{"units": "Percent change", "country": "Tuvalu", "percent": 0, "desc": "Volume of imports of goods and services"}
{"units": "Percent change", "country": "Uganda", "percent": 27.393, "desc": "Volume of imports of goods and services"}
{"units": "Percent change", "country": "Ukraine", "percent": 0, "desc": "Volume of imports of goods and services"}
{"units": "Percent change", "country": "United Arab Emirates", "percent": 4.305, "desc": "Volume of imports of goods and services"}
{"units": "Percent change", "country": "United Kingdom", "percent": 7.924, "desc": "Volume of imports of goods and services"}
{"units": "Percent change", "country": "United States", "percent": 5.923, "desc": "Volume of imports of goods and services"}
{"units": "Percent change", "country": "Uruguay", "percent": 15.803, "desc": "Volume of imports of goods and services"}
{"units": "Percent change", "country": "Uzbekistan", "percent": 0, "desc": "Volume of imports of goods and services"}
{"units": "Percent change", "country": "Vanuatu", "percent": 0, "desc": "Volume of imports of goods and services"}
{"units": "Percent change", "country": "Venezuela", "percent": 8.623, "desc": "Volume of imports of goods and services"}
{"units": "Percent change", "country": "Vietnam", "percent": -10.247, "desc": "Volume of imports of goods and services"}
{"units": "Percent change", "country": "Yemen", "percent": 0, "desc": "Volume of imports of goods and services"}
{"units": "Percent change", "country": "Zambia", "percent": 0, "desc": "Volume of imports of goods and services"}
{"units": "Percent change", "country": "Zimbabwe", "percent": 0, "desc": "Volume of imports of goods and services"}
