{"units": "", "country": "\u00a0Shaded cells indicate IMF staff estimates", "percent": 0, "desc": ""}
{"units": "", "country": "", "percent": 0, "desc": ""}
{"units": "Percent change", "country": "Afghanistan", "percent": 0, "desc": "Volume of exports of goods and services"}
{"units": "Percent change", "country": "Albania", "percent": 0.0, "desc": "Volume of exports of goods and services"}
{"units": "Percent change", "country": "Algeria", "percent": 0.3, "desc": "Volume of exports of goods and services"}
{"units": "Percent change", "country": "Angola", "percent": -12.9, "desc": "Volume of exports of goods and services"}
{"units": "Percent change", "country": "Antigua and Barbuda", "percent": 0, "desc": "Volume of exports of goods and services"}
{"units": "Percent change", "country": "Argentina", "percent": 3.947, "desc": "Volume of exports of goods and services"}
{"units": "Percent change", "country": "Armenia", "percent": 0, "desc": "Volume of exports of goods and services"}
{"units": "Percent change", "country": "Australia", "percent": 8.771, "desc": "Volume of exports of goods and services"}
{"units": "Percent change", "country": "Austria", "percent": 1.591, "desc": "Volume of exports of goods and services"}
{"units": "Percent change", "country": "Azerbaijan", "percent": 0, "desc": "Volume of exports of goods and services"}
{"units": "Percent change", "country": "The Bahamas", "percent": -1.704, "desc": "Volume of exports of goods and services"}
{"units": "Percent change", "country": "Bahrain", "percent": 0, "desc": "Volume of exports of goods and services"}
{"units": "Percent change", "country": "Bangladesh", "percent": 12.297, "desc": "Volume of exports of goods and services"}
{"units": "Percent change", "country": "Barbados", "percent": 8.08, "desc": "Volume of exports of goods and services"}
{"units": "Percent change", "country": "Belarus", "percent": 0, "desc": "Volume of exports of goods and services"}
{"units": "Percent change", "country": "Belgium", "percent": 3.555, "desc": "Volume of exports of goods and services"}
{"units": "Percent change", "country": "Belize", "percent": 0.0, "desc": "Volume of exports of goods and services"}
{"units": "Percent change", "country": "Benin", "percent": 1.976, "desc": "Volume of exports of goods and services"}
{"units": "Percent change", "country": "Bhutan", "percent": -25.374, "desc": "Volume of exports of goods and services"}
{"units": "Percent change", "country": "Bolivia", "percent": -13.122, "desc": "Volume of exports of goods and services"}
{"units": "Percent change", "country": "Bosnia and Herzegovina", "percent": 0, "desc": "Volume of exports of goods and services"}
{"units": "Percent change", "country": "Botswana", "percent": 28.946, "desc": "Volume of exports of goods and services"}
{"units": "Percent change", "country": "Brazil", "percent": -10.607, "desc": "Volume of exports of goods and services"}
{"units": "Percent change", "country": "Brunei Darussalam", "percent": 0, "desc": "Volume of exports of goods and services"}
{"units": "Percent change", "country": "Bulgaria", "percent": -3.596, "desc": "Volume of exports of goods and services"}
{"units": "Percent change", "country": "Burkina Faso", "percent": -30.29, "desc": "Volume of exports of goods and services"}
{"units": "Percent change", "country": "Burundi", "percent": 11.543, "desc": "Volume of exports of goods and services"}
{"units": "Percent change", "country": "Cabo Verde", "percent": -15.1, "desc": "Volume of exports of goods and services"}
{"units": "Percent change", "country": "Cambodia", "percent": 0, "desc": "Volume of exports of goods and services"}
{"units": "Percent change", "country": "Cameroon", "percent": 19.689, "desc": "Volume of exports of goods and services"}
{"units": "Percent change", "country": "Canada", "percent": -1.413, "desc": "Volume of exports of goods and services"}
{"units": "Percent change", "country": "Central African Republic", "percent": -0.863, "desc": "Volume of exports of goods and services"}
{"units": "Percent change", "country": "Chad", "percent": 8.023, "desc": "Volume of exports of goods and services"}
{"units": "Percent change", "country": "Chile", "percent": 4.49, "desc": "Volume of exports of goods and services"}
{"units": "Percent change", "country": "China", "percent": 0, "desc": "Volume of exports of goods and services"}
{"units": "Percent change", "country": "Colombia", "percent": 8.549, "desc": "Volume of exports of goods and services"}
{"units": "Percent change", "country": "Comoros", "percent": 27.678, "desc": "Volume of exports of goods and services"}
{"units": "Percent change", "country": "Democratic Republic of the Congo", "percent": 0, "desc": "Volume of exports of goods and services"}
{"units": "Percent change", "country": "Republic of Congo", "percent": -14.57, "desc": "Volume of exports of goods and services"}
{"units": "Percent change", "country": "Costa Rica", "percent": -4.229, "desc": "Volume of exports of goods and services"}
{"units": "Percent change", "country": "C\u00f4te d'Ivoire", "percent": 5.0, "desc": "Volume of exports of goods and services"}
{"units": "Percent change", "country": "Croatia", "percent": 0, "desc": "Volume of exports of goods and services"}
{"units": "Percent change", "country": "Cyprus", "percent": -2.302, "desc": "Volume of exports of goods and services"}
{"units": "Percent change", "country": "Czech Republic", "percent": 0, "desc": "Volume of exports of goods and services"}
{"units": "Percent change", "country": "Denmark", "percent": 3.164, "desc": "Volume of exports of goods and services"}
{"units": "Percent change", "country": "Djibouti", "percent": 0, "desc": "Volume of exports of goods and services"}
{"units": "Percent change", "country": "Dominica", "percent": 26.268, "desc": "Volume of exports of goods and services"}
{"units": "Percent change", "country": "Dominican Republic", "percent": -26.053, "desc": "Volume of exports of goods and services"}
{"units": "Percent change", "country": "Ecuador", "percent": -3.783, "desc": "Volume of exports of goods and services"}
{"units": "Percent change", "country": "Egypt", "percent": 8.354, "desc": "Volume of exports of goods and services"}
{"units": "Percent change", "country": "El Salvador", "percent": -14.851, "desc": "Volume of exports of goods and services"}
{"units": "Percent change", "country": "Equatorial Guinea", "percent": -26.461, "desc": "Volume of exports of goods and services"}
{"units": "Percent change", "country": "Eritrea", "percent": 0, "desc": "Volume of exports of goods and services"}
{"units": "Percent change", "country": "Estonia", "percent": 0, "desc": "Volume of exports of goods and services"}
{"units": "Percent change", "country": "Ethiopia", "percent": -3.126, "desc": "Volume of exports of goods and services"}
{"units": "Percent change", "country": "Fiji", "percent": 0, "desc": "Volume of exports of goods and services"}
{"units": "Percent change", "country": "Finland", "percent": -1.87, "desc": "Volume of exports of goods and services"}
{"units": "Percent change", "country": "France", "percent": -1.102, "desc": "Volume of exports of goods and services"}
{"units": "Percent change", "country": "Gabon", "percent": 1.714, "desc": "Volume of exports of goods and services"}
{"units": "Percent change", "country": "The Gambia", "percent": 0, "desc": "Volume of exports of goods and services"}
{"units": "Percent change", "country": "Georgia", "percent": 0, "desc": "Volume of exports of goods and services"}
{"units": "Percent change", "country": "Germany", "percent": 3.738, "desc": "Volume of exports of goods and services"}
{"units": "Percent change", "country": "Ghana", "percent": -33.0, "desc": "Volume of exports of goods and services"}
{"units": "Percent change", "country": "Greece", "percent": -16.461, "desc": "Volume of exports of goods and services"}
{"units": "Percent change", "country": "Grenada", "percent": 23.671, "desc": "Volume of exports of goods and services"}
{"units": "Percent change", "country": "Guatemala", "percent": -10.711, "desc": "Volume of exports of goods and services"}
{"units": "Percent change", "country": "Guinea", "percent": 0, "desc": "Volume of exports of goods and services"}
{"units": "Percent change", "country": "Guinea-Bissau", "percent": -0.6, "desc": "Volume of exports of goods and services"}
{"units": "Percent change", "country": "Guyana", "percent": -23.684, "desc": "Volume of exports of goods and services"}
{"units": "Percent change", "country": "Haiti", "percent": 17.525, "desc": "Volume of exports of goods and services"}
{"units": "Percent change", "country": "Honduras", "percent": -16.845, "desc": "Volume of exports of goods and services"}
{"units": "Percent change", "country": "Hong Kong SAR", "percent": -0.942, "desc": "Volume of exports of goods and services"}
{"units": "Percent change", "country": "Hungary", "percent": 3.54, "desc": "Volume of exports of goods and services"}
{"units": "Percent change", "country": "Iceland", "percent": -8.943, "desc": "Volume of exports of goods and services"}
{"units": "Percent change", "country": "India", "percent": 8.061, "desc": "Volume of exports of goods and services"}
{"units": "Percent change", "country": "Indonesia", "percent": -25.0, "desc": "Volume of exports of goods and services"}
{"units": "Percent change", "country": "Islamic Republic of Iran", "percent": 135.474, "desc": "Volume of exports of goods and services"}
{"units": "Percent change", "country": "Iraq", "percent": 0, "desc": "Volume of exports of goods and services"}
{"units": "Percent change", "country": "Ireland", "percent": 4.482, "desc": "Volume of exports of goods and services"}
{"units": "Percent change", "country": "Israel", "percent": -2.955, "desc": "Volume of exports of goods and services"}
{"units": "Percent change", "country": "Italy", "percent": -1.305, "desc": "Volume of exports of goods and services"}
{"units": "Percent change", "country": "Jamaica", "percent": -12.49, "desc": "Volume of exports of goods and services"}
{"units": "Percent change", "country": "Japan", "percent": 1.432, "desc": "Volume of exports of goods and services"}
{"units": "Percent change", "country": "Jordan", "percent": -10.433, "desc": "Volume of exports of goods and services"}
{"units": "Percent change", "country": "Kazakhstan", "percent": 0, "desc": "Volume of exports of goods and services"}
{"units": "Percent change", "country": "Kenya", "percent": 3.2, "desc": "Volume of exports of goods and services"}
{"units": "Percent change", "country": "Kiribati", "percent": -7.19, "desc": "Volume of exports of goods and services"}
{"units": "Percent change", "country": "Korea", "percent": 8.19, "desc": "Volume of exports of goods and services"}
{"units": "Percent change", "country": "Kosovo", "percent": 0, "desc": "Volume of exports of goods and services"}
{"units": "Percent change", "country": "Kuwait", "percent": -28.848, "desc": "Volume of exports of goods and services"}
{"units": "Percent change", "country": "Kyrgyz Republic", "percent": 0, "desc": "Volume of exports of goods and services"}
{"units": "Percent change", "country": "Lao P.D.R.", "percent": 66.915, "desc": "Volume of exports of goods and services"}
{"units": "Percent change", "country": "Latvia", "percent": 0, "desc": "Volume of exports of goods and services"}
{"units": "Percent change", "country": "Lebanon", "percent": 43.328, "desc": "Volume of exports of goods and services"}
{"units": "Percent change", "country": "Lesotho", "percent": 0.0, "desc": "Volume of exports of goods and services"}
{"units": "Percent change", "country": "Liberia", "percent": 0, "desc": "Volume of exports of goods and services"}
{"units": "Percent change", "country": "Libya", "percent": 0, "desc": "Volume of exports of goods and services"}
{"units": "Percent change", "country": "Lithuania", "percent": 0, "desc": "Volume of exports of goods and services"}
{"units": "Percent change", "country": "Luxembourg", "percent": 0, "desc": "Volume of exports of goods and services"}
{"units": "Percent change", "country": "Macao SAR", "percent": 0, "desc": "Volume of exports of goods and services"}
{"units": "Percent change", "country": "FYR Macedonia", "percent": 0, "desc": "Volume of exports of goods and services"}
{"units": "Percent change", "country": "Madagascar", "percent": 0.0, "desc": "Volume of exports of goods and services"}
{"units": "Percent change", "country": "Malawi", "percent": -10.009, "desc": "Volume of exports of goods and services"}
{"units": "Percent change", "country": "Malaysia", "percent": 9.886, "desc": "Volume of exports of goods and services"}
{"units": "Percent change", "country": "Maldives", "percent": 4.474, "desc": "Volume of exports of goods and services"}
{"units": "Percent change", "country": "Mali", "percent": 11.585, "desc": "Volume of exports of goods and services"}
{"units": "Percent change", "country": "Malta", "percent": -15.656, "desc": "Volume of exports of goods and services"}
{"units": "Percent change", "country": "Marshall Islands", "percent": 0, "desc": "Volume of exports of goods and services"}
{"units": "Percent change", "country": "Mauritania", "percent": 0, "desc": "Volume of exports of goods and services"}
{"units": "Percent change", "country": "Mauritius", "percent": 2.309, "desc": "Volume of exports of goods and services"}
{"units": "Percent change", "country": "Mexico", "percent": 22.636, "desc": "Volume of exports of goods and services"}
{"units": "Percent change", "country": "Micronesia", "percent": 0, "desc": "Volume of exports of goods and services"}
{"units": "Percent change", "country": "Moldova", "percent": 0, "desc": "Volume of exports of goods and services"}
{"units": "Percent change", "country": "Mongolia", "percent": 0, "desc": "Volume of exports of goods and services"}
{"units": "Percent change", "country": "Montenegro", "percent": 0, "desc": "Volume of exports of goods and services"}
{"units": "Percent change", "country": "Morocco", "percent": 4.648, "desc": "Volume of exports of goods and services"}
{"units": "Percent change", "country": "Mozambique", "percent": -7.304, "desc": "Volume of exports of goods and services"}
{"units": "Percent change", "country": "Myanmar", "percent": 0, "desc": "Volume of exports of goods and services"}
{"units": "Percent change", "country": "Namibia", "percent": 0, "desc": "Volume of exports of goods and services"}
{"units": "Percent change", "country": "Nepal", "percent": 0, "desc": "Volume of exports of goods and services"}
{"units": "Percent change", "country": "Netherlands", "percent": -0.017, "desc": "Volume of exports of goods and services"}
{"units": "Percent change", "country": "New Zealand", "percent": 2.218, "desc": "Volume of exports of goods and services"}
{"units": "Percent change", "country": "Nicaragua", "percent": 0, "desc": "Volume of exports of goods and services"}
{"units": "Percent change", "country": "Niger", "percent": -14.26, "desc": "Volume of exports of goods and services"}
{"units": "Percent change", "country": "Nigeria", "percent": 0, "desc": "Volume of exports of goods and services"}
{"units": "Percent change", "country": "Norway", "percent": 0.131, "desc": "Volume of exports of goods and services"}
{"units": "Percent change", "country": "Oman", "percent": 1.078, "desc": "Volume of exports of goods and services"}
{"units": "Percent change", "country": "Pakistan", "percent": 11.153, "desc": "Volume of exports of goods and services"}
{"units": "Percent change", "country": "Palau", "percent": 0, "desc": "Volume of exports of goods and services"}
{"units": "Percent change", "country": "Panama", "percent": 6.061, "desc": "Volume of exports of goods and services"}
{"units": "Percent change", "country": "Papua New Guinea", "percent": 0, "desc": "Volume of exports of goods and services"}
{"units": "Percent change", "country": "Paraguay", "percent": 7.3, "desc": "Volume of exports of goods and services"}
{"units": "Percent change", "country": "Peru", "percent": -9.674, "desc": "Volume of exports of goods and services"}
{"units": "Percent change", "country": "Philippines", "percent": -5.907, "desc": "Volume of exports of goods and services"}
{"units": "Percent change", "country": "Poland", "percent": 0, "desc": "Volume of exports of goods and services"}
{"units": "Percent change", "country": "Portugal", "percent": 4.833, "desc": "Volume of exports of goods and services"}
{"units": "Percent change", "country": "Puerto Rico", "percent": 0, "desc": "Volume of exports of goods and services"}
{"units": "Percent change", "country": "Qatar", "percent": -14.463, "desc": "Volume of exports of goods and services"}
{"units": "Percent change", "country": "Romania", "percent": -8.913, "desc": "Volume of exports of goods and services"}
{"units": "Percent change", "country": "Russia", "percent": 0, "desc": "Volume of exports of goods and services"}
{"units": "Percent change", "country": "Rwanda", "percent": -16.182, "desc": "Volume of exports of goods and services"}
{"units": "Percent change", "country": "Samoa", "percent": 0, "desc": "Volume of exports of goods and services"}
{"units": "Percent change", "country": "San Marino", "percent": 0, "desc": "Volume of exports of goods and services"}
{"units": "Percent change", "country": "S\u00e3o Tom\u00e9 and Pr\u00edncipe", "percent": 0.0, "desc": "Volume of exports of goods and services"}
{"units": "Percent change", "country": "Saudi Arabia", "percent": -27.359, "desc": "Volume of exports of goods and services"}
{"units": "Percent change", "country": "Senegal", "percent": 28.568, "desc": "Volume of exports of goods and services"}
{"units": "Percent change", "country": "Serbia", "percent": 0, "desc": "Volume of exports of goods and services"}
{"units": "Percent change", "country": "Seychelles", "percent": 0.796, "desc": "Volume of exports of goods and services"}
{"units": "Percent change", "country": "Sierra Leone", "percent": -30.085, "desc": "Volume of exports of goods and services"}
{"units": "Percent change", "country": "Singapore", "percent": 5.161, "desc": "Volume of exports of goods and services"}
{"units": "Percent change", "country": "Slovak Republic", "percent": 0, "desc": "Volume of exports of goods and services"}
{"units": "Percent change", "country": "Slovenia", "percent": 0, "desc": "Volume of exports of goods and services"}
{"units": "Percent change", "country": "Solomon Islands", "percent": -20.674, "desc": "Volume of exports of goods and services"}
{"units": "Percent change", "country": "South Africa", "percent": -2.645, "desc": "Volume of exports of goods and services"}
{"units": "Percent change", "country": "South Sudan", "percent": 0, "desc": "Volume of exports of goods and services"}
{"units": "Percent change", "country": "Spain", "percent": 5.573, "desc": "Volume of exports of goods and services"}
{"units": "Percent change", "country": "Sri Lanka", "percent": 5.195, "desc": "Volume of exports of goods and services"}
{"units": "Percent change", "country": "St. Kitts and Nevis", "percent": -12.424, "desc": "Volume of exports of goods and services"}
{"units": "Percent change", "country": "St. Lucia", "percent": 6.519, "desc": "Volume of exports of goods and services"}
{"units": "Percent change", "country": "St. Vincent and the Grenadines", "percent": -5.742, "desc": "Volume of exports of goods and services"}
{"units": "Percent change", "country": "Sudan", "percent": 0.468, "desc": "Volume of exports of goods and services"}
{"units": "Percent change", "country": "Suriname", "percent": -2.832, "desc": "Volume of exports of goods and services"}
{"units": "Percent change", "country": "Swaziland", "percent": -11.915, "desc": "Volume of exports of goods and services"}
{"units": "Percent change", "country": "Sweden", "percent": -15.925, "desc": "Volume of exports of goods and services"}
{"units": "Percent change", "country": "Switzerland", "percent": -2.379, "desc": "Volume of exports of goods and services"}
{"units": "Percent change", "country": "Syria", "percent": 4.2, "desc": "Volume of exports of goods and services"}
{"units": "Percent change", "country": "Taiwan Province of China", "percent": 1.924, "desc": "Volume of exports of goods and services"}
{"units": "Percent change", "country": "Tajikistan", "percent": 0, "desc": "Volume of exports of goods and services"}
{"units": "Percent change", "country": "Tanzania", "percent": -24.6, "desc": "Volume of exports of goods and services"}
{"units": "Percent change", "country": "Thailand", "percent": 18.788, "desc": "Volume of exports of goods and services"}
{"units": "Percent change", "country": "Timor-Leste", "percent": 0, "desc": "Volume of exports of goods and services"}
{"units": "Percent change", "country": "Togo", "percent": 0, "desc": "Volume of exports of goods and services"}
{"units": "Percent change", "country": "Tonga", "percent": 0, "desc": "Volume of exports of goods and services"}
{"units": "Percent change", "country": "Trinidad and Tobago", "percent": -3.837, "desc": "Volume of exports of goods and services"}
{"units": "Percent change", "country": "Tunisia", "percent": -6.901, "desc": "Volume of exports of goods and services"}
{"units": "Percent change", "country": "Turkey", "percent": 0, "desc": "Volume of exports of goods and services"}
{"units": "Percent change", "country": "Turkmenistan", "percent": 0, "desc": "Volume of exports of goods and services"}
{"units": "Percent change", "country": "Tuvalu", "percent": 0, "desc": "Volume of exports of goods and services"}
{"units": "Percent change", "country": "Uganda", "percent": 53.961, "desc": "Volume of exports of goods and services"}
{"units": "Percent change", "country": "Ukraine", "percent": 0, "desc": "Volume of exports of goods and services"}
{"units": "Percent change", "country": "United Arab Emirates", "percent": -8.81, "desc": "Volume of exports of goods and services"}
{"units": "Percent change", "country": "United Kingdom", "percent": 1.113, "desc": "Volume of exports of goods and services"}
{"units": "Percent change", "country": "United States", "percent": -7.639, "desc": "Volume of exports of goods and services"}
{"units": "Percent change", "country": "Uruguay", "percent": -16.485, "desc": "Volume of exports of goods and services"}
{"units": "Percent change", "country": "Uzbekistan", "percent": 0, "desc": "Volume of exports of goods and services"}
{"units": "Percent change", "country": "Vanuatu", "percent": 0, "desc": "Volume of exports of goods and services"}
{"units": "Percent change", "country": "Venezuela", "percent": 0, "desc": "Volume of exports of goods and services"}
{"units": "Percent change", "country": "Vietnam", "percent": 45.337, "desc": "Volume of exports of goods and services"}
{"units": "Percent change", "country": "Yemen", "percent": 0, "desc": "Volume of exports of goods and services"}
{"units": "Percent change", "country": "Zambia", "percent": 0, "desc": "Volume of exports of goods and services"}
{"units": "Percent change", "country": "Zimbabwe", "percent": 0, "desc": "Volume of exports of goods and services"}
