{"units": "", "country": "\u00a0Shaded cells indicate IMF staff estimates", "percent": 0, "desc": ""}
{"units": "", "country": "", "percent": 0, "desc": ""}
{"units": "Percent change", "country": "Afghanistan", "percent": 0, "desc": "Inflation, end of period consumer prices"}
{"units": "Percent change", "country": "Albania", "percent": 236.58, "desc": "Inflation, end of period consumer prices"}
{"units": "Percent change", "country": "Algeria", "percent": 31.7, "desc": "Inflation, end of period consumer prices"}
{"units": "Percent change", "country": "Angola", "percent": 495.793, "desc": "Inflation, end of period consumer prices"}
{"units": "Percent change", "country": "Antigua and Barbuda", "percent": 2.862, "desc": "Inflation, end of period consumer prices"}
{"units": "Percent change", "country": "Argentina", "percent": 17.546, "desc": "Inflation, end of period consumer prices"}
{"units": "Percent change", "country": "Armenia", "percent": 0, "desc": "Inflation, end of period consumer prices"}
{"units": "Percent change", "country": "Australia", "percent": 0.334, "desc": "Inflation, end of period consumer prices"}
{"units": "Percent change", "country": "Austria", "percent": 3.741, "desc": "Inflation, end of period consumer prices"}
{"units": "Percent change", "country": "Azerbaijan", "percent": 0, "desc": "Inflation, end of period consumer prices"}
{"units": "Percent change", "country": "The Bahamas", "percent": 3.505, "desc": "Inflation, end of period consumer prices"}
{"units": "Percent change", "country": "Bahrain", "percent": 1.146, "desc": "Inflation, end of period consumer prices"}
{"units": "Percent change", "country": "Bangladesh", "percent": 1.505, "desc": "Inflation, end of period consumer prices"}
{"units": "Percent change", "country": "Barbados", "percent": 3.302, "desc": "Inflation, end of period consumer prices"}
{"units": "Percent change", "country": "Belarus", "percent": 0, "desc": "Inflation, end of period consumer prices"}
{"units": "Percent change", "country": "Belgium", "percent": 2.184, "desc": "Inflation, end of period consumer prices"}
{"units": "Percent change", "country": "Belize", "percent": 2.032, "desc": "Inflation, end of period consumer prices"}
{"units": "Percent change", "country": "Benin", "percent": 2.51, "desc": "Inflation, end of period consumer prices"}
{"units": "Percent change", "country": "Bhutan", "percent": 14.695, "desc": "Inflation, end of period consumer prices"}
{"units": "Percent change", "country": "Bolivia", "percent": 10.462, "desc": "Inflation, end of period consumer prices"}
{"units": "Percent change", "country": "Bosnia and Herzegovina", "percent": 0, "desc": "Inflation, end of period consumer prices"}
{"units": "Percent change", "country": "Botswana", "percent": 16.5, "desc": "Inflation, end of period consumer prices"}
{"units": "Percent change", "country": "Brazil", "percent": 1119.092, "desc": "Inflation, end of period consumer prices"}
{"units": "Percent change", "country": "Brunei Darussalam", "percent": 1.259, "desc": "Inflation, end of period consumer prices"}
{"units": "Percent change", "country": "Bulgaria", "percent": 79.416, "desc": "Inflation, end of period consumer prices"}
{"units": "Percent change", "country": "Burkina Faso", "percent": -0.163, "desc": "Inflation, end of period consumer prices"}
{"units": "Percent change", "country": "Burundi", "percent": 3.522, "desc": "Inflation, end of period consumer prices"}
{"units": "Percent change", "country": "Cabo Verde", "percent": 13.91, "desc": "Inflation, end of period consumer prices"}
{"units": "Percent change", "country": "Cambodia", "percent": 112.0, "desc": "Inflation, end of period consumer prices"}
{"units": "Percent change", "country": "Cameroon", "percent": 0.751, "desc": "Inflation, end of period consumer prices"}
{"units": "Percent change", "country": "Canada", "percent": 1.788, "desc": "Inflation, end of period consumer prices"}
{"units": "Percent change", "country": "Central African Republic", "percent": 0.0, "desc": "Inflation, end of period consumer prices"}
{"units": "Percent change", "country": "Chad", "percent": -6.8, "desc": "Inflation, end of period consumer prices"}
{"units": "Percent change", "country": "Chile", "percent": 12.932, "desc": "Inflation, end of period consumer prices"}
{"units": "Percent change", "country": "China", "percent": 8.8, "desc": "Inflation, end of period consumer prices"}
{"units": "Percent change", "country": "Colombia", "percent": 25.108, "desc": "Inflation, end of period consumer prices"}
{"units": "Percent change", "country": "Comoros", "percent": 0, "desc": "Inflation, end of period consumer prices"}
{"units": "Percent change", "country": "Democratic Republic of the Congo", "percent": 2729.79, "desc": "Inflation, end of period consumer prices"}
{"units": "Percent change", "country": "Republic of Congo", "percent": -2.74, "desc": "Inflation, end of period consumer prices"}
{"units": "Percent change", "country": "Costa Rica", "percent": 16.937, "desc": "Inflation, end of period consumer prices"}
{"units": "Percent change", "country": "C\u00f4te d'Ivoire", "percent": 3.568, "desc": "Inflation, end of period consumer prices"}
{"units": "Percent change", "country": "Croatia", "percent": 0, "desc": "Inflation, end of period consumer prices"}
{"units": "Percent change", "country": "Cyprus", "percent": 6.491, "desc": "Inflation, end of period consumer prices"}
{"units": "Percent change", "country": "Czech Republic", "percent": 0, "desc": "Inflation, end of period consumer prices"}
{"units": "Percent change", "country": "Denmark", "percent": 1.655, "desc": "Inflation, end of period consumer prices"}
{"units": "Percent change", "country": "Djibouti", "percent": 3.869, "desc": "Inflation, end of period consumer prices"}
{"units": "Percent change", "country": "Dominica", "percent": 4.314, "desc": "Inflation, end of period consumer prices"}
{"units": "Percent change", "country": "Dominican Republic", "percent": 5.165, "desc": "Inflation, end of period consumer prices"}
{"units": "Percent change", "country": "Ecuador", "percent": 60.2, "desc": "Inflation, end of period consumer prices"}
{"units": "Percent change", "country": "Egypt", "percent": 9.744, "desc": "Inflation, end of period consumer prices"}
{"units": "Percent change", "country": "El Salvador", "percent": 19.937, "desc": "Inflation, end of period consumer prices"}
{"units": "Percent change", "country": "Equatorial Guinea", "percent": 2.82, "desc": "Inflation, end of period consumer prices"}
{"units": "Percent change", "country": "Eritrea", "percent": 0, "desc": "Inflation, end of period consumer prices"}
{"units": "Percent change", "country": "Estonia", "percent": 0, "desc": "Inflation, end of period consumer prices"}
{"units": "Percent change", "country": "Ethiopia", "percent": 2.053, "desc": "Inflation, end of period consumer prices"}
{"units": "Percent change", "country": "Fiji", "percent": 0, "desc": "Inflation, end of period consumer prices"}
{"units": "Percent change", "country": "Finland", "percent": 2.603, "desc": "Inflation, end of period consumer prices"}
{"units": "Percent change", "country": "France", "percent": 2.01, "desc": "Inflation, end of period consumer prices"}
{"units": "Percent change", "country": "Gabon", "percent": -4.532, "desc": "Inflation, end of period consumer prices"}
{"units": "Percent change", "country": "The Gambia", "percent": 4.246, "desc": "Inflation, end of period consumer prices"}
{"units": "Percent change", "country": "Georgia", "percent": 0, "desc": "Inflation, end of period consumer prices"}
{"units": "Percent change", "country": "Germany", "percent": 3.3, "desc": "Inflation, end of period consumer prices"}
{"units": "Percent change", "country": "Ghana", "percent": 13.33, "desc": "Inflation, end of period consumer prices"}
{"units": "Percent change", "country": "Greece", "percent": 14.532, "desc": "Inflation, end of period consumer prices"}
{"units": "Percent change", "country": "Grenada", "percent": 0.969, "desc": "Inflation, end of period consumer prices"}
{"units": "Percent change", "country": "Guatemala", "percent": 14.2, "desc": "Inflation, end of period consumer prices"}
{"units": "Percent change", "country": "Guinea", "percent": 16.1, "desc": "Inflation, end of period consumer prices"}
{"units": "Percent change", "country": "Guinea-Bissau", "percent": 86.697, "desc": "Inflation, end of period consumer prices"}
{"units": "Percent change", "country": "Guyana", "percent": 12.5, "desc": "Inflation, end of period consumer prices"}
{"units": "Percent change", "country": "Haiti", "percent": 15.181, "desc": "Inflation, end of period consumer prices"}
{"units": "Percent change", "country": "Honduras", "percent": 6.429, "desc": "Inflation, end of period consumer prices"}
{"units": "Percent change", "country": "Hong Kong SAR", "percent": 9.697, "desc": "Inflation, end of period consumer prices"}
{"units": "Percent change", "country": "Hungary", "percent": 21.6, "desc": "Inflation, end of period consumer prices"}
{"units": "Percent change", "country": "Iceland", "percent": 1.507, "desc": "Inflation, end of period consumer prices"}
{"units": "Percent change", "country": "India", "percent": 5.831, "desc": "Inflation, end of period consumer prices"}
{"units": "Percent change", "country": "Indonesia", "percent": 5.039, "desc": "Inflation, end of period consumer prices"}
{"units": "Percent change", "country": "Islamic Republic of Iran", "percent": 21.945, "desc": "Inflation, end of period consumer prices"}
{"units": "Percent change", "country": "Iraq", "percent": 0, "desc": "Inflation, end of period consumer prices"}
{"units": "Percent change", "country": "Ireland", "percent": 0, "desc": "Inflation, end of period consumer prices"}
{"units": "Percent change", "country": "Israel", "percent": 9.37, "desc": "Inflation, end of period consumer prices"}
{"units": "Percent change", "country": "Italy", "percent": 4.651, "desc": "Inflation, end of period consumer prices"}
{"units": "Percent change", "country": "Jamaica", "percent": 40.194, "desc": "Inflation, end of period consumer prices"}
{"units": "Percent change", "country": "Japan", "percent": 0.93, "desc": "Inflation, end of period consumer prices"}
{"units": "Percent change", "country": "Jordan", "percent": 3.659, "desc": "Inflation, end of period consumer prices"}
{"units": "Percent change", "country": "Kazakhstan", "percent": 0, "desc": "Inflation, end of period consumer prices"}
{"units": "Percent change", "country": "Kenya", "percent": 33.668, "desc": "Inflation, end of period consumer prices"}
{"units": "Percent change", "country": "Kiribati", "percent": 4.217, "desc": "Inflation, end of period consumer prices"}
{"units": "Percent change", "country": "Korea", "percent": 4.458, "desc": "Inflation, end of period consumer prices"}
{"units": "Percent change", "country": "Kosovo", "percent": 0, "desc": "Inflation, end of period consumer prices"}
{"units": "Percent change", "country": "Kuwait", "percent": -0.881, "desc": "Inflation, end of period consumer prices"}
{"units": "Percent change", "country": "Kyrgyz Republic", "percent": 0, "desc": "Inflation, end of period consumer prices"}
{"units": "Percent change", "country": "Lao P.D.R.", "percent": 6.003, "desc": "Inflation, end of period consumer prices"}
{"units": "Percent change", "country": "Latvia", "percent": 0, "desc": "Inflation, end of period consumer prices"}
{"units": "Percent change", "country": "Lebanon", "percent": 110.047, "desc": "Inflation, end of period consumer prices"}
{"units": "Percent change", "country": "Lesotho", "percent": 15.298, "desc": "Inflation, end of period consumer prices"}
{"units": "Percent change", "country": "Liberia", "percent": 0, "desc": "Inflation, end of period consumer prices"}
{"units": "Percent change", "country": "Libya", "percent": 9.45, "desc": "Inflation, end of period consumer prices"}
{"units": "Percent change", "country": "Lithuania", "percent": 0, "desc": "Inflation, end of period consumer prices"}
{"units": "Percent change", "country": "Luxembourg", "percent": 2.904, "desc": "Inflation, end of period consumer prices"}
{"units": "Percent change", "country": "Macao SAR", "percent": 0, "desc": "Inflation, end of period consumer prices"}
{"units": "Percent change", "country": "FYR Macedonia", "percent": 0, "desc": "Inflation, end of period consumer prices"}
{"units": "Percent change", "country": "Madagascar", "percent": 16.074, "desc": "Inflation, end of period consumer prices"}
{"units": "Percent change", "country": "Malawi", "percent": 36.09, "desc": "Inflation, end of period consumer prices"}
{"units": "Percent change", "country": "Malaysia", "percent": 4.797, "desc": "Inflation, end of period consumer prices"}
{"units": "Percent change", "country": "Maldives", "percent": 12.447, "desc": "Inflation, end of period consumer prices"}
{"units": "Percent change", "country": "Mali", "percent": -4.214, "desc": "Inflation, end of period consumer prices"}
{"units": "Percent change", "country": "Malta", "percent": 2.446, "desc": "Inflation, end of period consumer prices"}
{"units": "Percent change", "country": "Marshall Islands", "percent": 0, "desc": "Inflation, end of period consumer prices"}
{"units": "Percent change", "country": "Mauritania", "percent": 17.562, "desc": "Inflation, end of period consumer prices"}
{"units": "Percent change", "country": "Mauritius", "percent": 6.379, "desc": "Inflation, end of period consumer prices"}
{"units": "Percent change", "country": "Mexico", "percent": 11.938, "desc": "Inflation, end of period consumer prices"}
{"units": "Percent change", "country": "Micronesia", "percent": 0, "desc": "Inflation, end of period consumer prices"}
{"units": "Percent change", "country": "Moldova", "percent": 0, "desc": "Inflation, end of period consumer prices"}
{"units": "Percent change", "country": "Mongolia", "percent": 321.0, "desc": "Inflation, end of period consumer prices"}
{"units": "Percent change", "country": "Montenegro", "percent": 0, "desc": "Inflation, end of period consumer prices"}
{"units": "Percent change", "country": "Morocco", "percent": 3.895, "desc": "Inflation, end of period consumer prices"}
{"units": "Percent change", "country": "Mozambique", "percent": 54.5, "desc": "Inflation, end of period consumer prices"}
{"units": "Percent change", "country": "Myanmar", "percent": 0, "desc": "Inflation, end of period consumer prices"}
{"units": "Percent change", "country": "Namibia", "percent": 12.127, "desc": "Inflation, end of period consumer prices"}
{"units": "Percent change", "country": "Nepal", "percent": 19.3, "desc": "Inflation, end of period consumer prices"}
{"units": "Percent change", "country": "Netherlands", "percent": 1.613, "desc": "Inflation, end of period consumer prices"}
{"units": "Percent change", "country": "New Zealand", "percent": 1.355, "desc": "Inflation, end of period consumer prices"}
{"units": "Percent change", "country": "Nicaragua", "percent": 0, "desc": "Inflation, end of period consumer prices"}
{"units": "Percent change", "country": "Niger", "percent": -2.617, "desc": "Inflation, end of period consumer prices"}
{"units": "Percent change", "country": "Nigeria", "percent": 0, "desc": "Inflation, end of period consumer prices"}
{"units": "Percent change", "country": "Norway", "percent": 2.176, "desc": "Inflation, end of period consumer prices"}
{"units": "Percent change", "country": "Oman", "percent": 1.047, "desc": "Inflation, end of period consumer prices"}
{"units": "Percent change", "country": "Pakistan", "percent": 14.464, "desc": "Inflation, end of period consumer prices"}
{"units": "Percent change", "country": "Palau", "percent": 0, "desc": "Inflation, end of period consumer prices"}
{"units": "Percent change", "country": "Panama", "percent": 1.649, "desc": "Inflation, end of period consumer prices"}
{"units": "Percent change", "country": "Papua New Guinea", "percent": 4.969, "desc": "Inflation, end of period consumer prices"}
{"units": "Percent change", "country": "Paraguay", "percent": 17.775, "desc": "Inflation, end of period consumer prices"}
{"units": "Percent change", "country": "Peru", "percent": 56.745, "desc": "Inflation, end of period consumer prices"}
{"units": "Percent change", "country": "Philippines", "percent": 7.374, "desc": "Inflation, end of period consumer prices"}
{"units": "Percent change", "country": "Poland", "percent": 44.432, "desc": "Inflation, end of period consumer prices"}
{"units": "Percent change", "country": "Portugal", "percent": 8.048, "desc": "Inflation, end of period consumer prices"}
{"units": "Percent change", "country": "Puerto Rico", "percent": 1.1, "desc": "Inflation, end of period consumer prices"}
{"units": "Percent change", "country": "Qatar", "percent": 0, "desc": "Inflation, end of period consumer prices"}
{"units": "Percent change", "country": "Romania", "percent": 199.213, "desc": "Inflation, end of period consumer prices"}
{"units": "Percent change", "country": "Russia", "percent": 0, "desc": "Inflation, end of period consumer prices"}
{"units": "Percent change", "country": "Rwanda", "percent": 14.495, "desc": "Inflation, end of period consumer prices"}
{"units": "Percent change", "country": "Samoa", "percent": 6.776, "desc": "Inflation, end of period consumer prices"}
{"units": "Percent change", "country": "San Marino", "percent": 0, "desc": "Inflation, end of period consumer prices"}
{"units": "Percent change", "country": "S\u00e3o Tom\u00e9 and Pr\u00edncipe", "percent": 27.335, "desc": "Inflation, end of period consumer prices"}
{"units": "Percent change", "country": "Saudi Arabia", "percent": -0.371, "desc": "Inflation, end of period consumer prices"}
{"units": "Percent change", "country": "Senegal", "percent": -0.496, "desc": "Inflation, end of period consumer prices"}
{"units": "Percent change", "country": "Serbia", "percent": 0, "desc": "Inflation, end of period consumer prices"}
{"units": "Percent change", "country": "Seychelles", "percent": 0.83, "desc": "Inflation, end of period consumer prices"}
{"units": "Percent change", "country": "Sierra Leone", "percent": 34.799, "desc": "Inflation, end of period consumer prices"}
{"units": "Percent change", "country": "Singapore", "percent": 1.79, "desc": "Inflation, end of period consumer prices"}
{"units": "Percent change", "country": "Slovak Republic", "percent": 0, "desc": "Inflation, end of period consumer prices"}
{"units": "Percent change", "country": "Slovenia", "percent": 0, "desc": "Inflation, end of period consumer prices"}
{"units": "Percent change", "country": "Solomon Islands", "percent": 0, "desc": "Inflation, end of period consumer prices"}
{"units": "Percent change", "country": "South Africa", "percent": 10.0, "desc": "Inflation, end of period consumer prices"}
{"units": "Percent change", "country": "South Sudan", "percent": 0, "desc": "Inflation, end of period consumer prices"}
{"units": "Percent change", "country": "Spain", "percent": 5.36, "desc": "Inflation, end of period consumer prices"}
{"units": "Percent change", "country": "Sri Lanka", "percent": 13.815, "desc": "Inflation, end of period consumer prices"}
{"units": "Percent change", "country": "St. Kitts and Nevis", "percent": 1.461, "desc": "Inflation, end of period consumer prices"}
{"units": "Percent change", "country": "St. Lucia", "percent": 3.156, "desc": "Inflation, end of period consumer prices"}
{"units": "Percent change", "country": "St. Vincent and the Grenadines", "percent": 3.073, "desc": "Inflation, end of period consumer prices"}
{"units": "Percent change", "country": "Sudan", "percent": 117.624, "desc": "Inflation, end of period consumer prices"}
{"units": "Percent change", "country": "Suriname", "percent": 33.025, "desc": "Inflation, end of period consumer prices"}
{"units": "Percent change", "country": "Swaziland", "percent": 8.567, "desc": "Inflation, end of period consumer prices"}
{"units": "Percent change", "country": "Sweden", "percent": 1.149, "desc": "Inflation, end of period consumer prices"}
{"units": "Percent change", "country": "Switzerland", "percent": 3.455, "desc": "Inflation, end of period consumer prices"}
{"units": "Percent change", "country": "Syria", "percent": 8.232, "desc": "Inflation, end of period consumer prices"}
{"units": "Percent change", "country": "Taiwan Province of China", "percent": 3.417, "desc": "Inflation, end of period consumer prices"}
{"units": "Percent change", "country": "Tajikistan", "percent": 0, "desc": "Inflation, end of period consumer prices"}
{"units": "Percent change", "country": "Tanzania", "percent": 20.736, "desc": "Inflation, end of period consumer prices"}
{"units": "Percent change", "country": "Thailand", "percent": 3.107, "desc": "Inflation, end of period consumer prices"}
{"units": "Percent change", "country": "Timor-Leste", "percent": 0, "desc": "Inflation, end of period consumer prices"}
{"units": "Percent change", "country": "Togo", "percent": -2.109, "desc": "Inflation, end of period consumer prices"}
{"units": "Percent change", "country": "Tonga", "percent": 8.418, "desc": "Inflation, end of period consumer prices"}
{"units": "Percent change", "country": "Trinidad and Tobago", "percent": 8.498, "desc": "Inflation, end of period consumer prices"}
{"units": "Percent change", "country": "Tunisia", "percent": 4.759, "desc": "Inflation, end of period consumer prices"}
{"units": "Percent change", "country": "Turkey", "percent": 65.967, "desc": "Inflation, end of period consumer prices"}
{"units": "Percent change", "country": "Turkmenistan", "percent": 0, "desc": "Inflation, end of period consumer prices"}
{"units": "Percent change", "country": "Tuvalu", "percent": 0, "desc": "Inflation, end of period consumer prices"}
{"units": "Percent change", "country": "Uganda", "percent": 66.31, "desc": "Inflation, end of period consumer prices"}
{"units": "Percent change", "country": "Ukraine", "percent": 0, "desc": "Inflation, end of period consumer prices"}
{"units": "Percent change", "country": "United Arab Emirates", "percent": 3.341, "desc": "Inflation, end of period consumer prices"}
{"units": "Percent change", "country": "United Kingdom", "percent": 2.602, "desc": "Inflation, end of period consumer prices"}
{"units": "Percent change", "country": "United States", "percent": 3.148, "desc": "Inflation, end of period consumer prices"}
{"units": "Percent change", "country": "Uruguay", "percent": 58.911, "desc": "Inflation, end of period consumer prices"}
{"units": "Percent change", "country": "Uzbekistan", "percent": 0, "desc": "Inflation, end of period consumer prices"}
{"units": "Percent change", "country": "Vanuatu", "percent": 5.142, "desc": "Inflation, end of period consumer prices"}
{"units": "Percent change", "country": "Venezuela", "percent": 31.857, "desc": "Inflation, end of period consumer prices"}
{"units": "Percent change", "country": "Vietnam", "percent": 17.605, "desc": "Inflation, end of period consumer prices"}
{"units": "Percent change", "country": "Yemen", "percent": 0, "desc": "Inflation, end of period consumer prices"}
{"units": "Percent change", "country": "Zambia", "percent": 180.715, "desc": "Inflation, end of period consumer prices"}
{"units": "Percent change", "country": "Zimbabwe", "percent": 0, "desc": "Inflation, end of period consumer prices"}
